{
  "n_total": 15886,
  "n_with_gex": 11702,
  "by_gex_position": [
    {
      "gex_above_or_below": "above_spot",
      "side": "call",
      "n": 3405,
      "win_pct": 20.88,
      "mean_pct": 0.01,
      "mean_dollar": -15.15
    },
    {
      "gex_above_or_below": "above_spot",
      "side": "put",
      "n": 5363,
      "win_pct": 2.46,
      "mean_pct": -0.78,
      "mean_dollar": -63.51
    },
    {
      "gex_above_or_below": "below_spot",
      "side": "call",
      "n": 503,
      "win_pct": 40.16,
      "mean_pct": 0.62,
      "mean_dollar": 401.1
    },
    {
      "gex_above_or_below": "below_spot",
      "side": "put",
      "n": 1381,
      "win_pct": 0.43,
      "mean_pct": -0.93,
      "mean_dollar": -193.94
    },
    {
      "gex_above_or_below": "missing",
      "side": "call",
      "n": 1042,
      "win_pct": 28.5,
      "mean_pct": -0.32,
      "mean_dollar": -92.77
    },
    {
      "gex_above_or_below": "missing",
      "side": "put",
      "n": 2429,
      "win_pct": 3.54,
      "mean_pct": -0.78,
      "mean_dollar": -178.81
    }
  ],
  "by_gex_zone": [
    {
      "alert_in_gex_zone": false,
      "side": "call",
      "n": 2434,
      "win_pct": 30.65,
      "mean_pct": -0.02,
      "mean_dollar": -36.31
    },
    {
      "alert_in_gex_zone": false,
      "side": "put",
      "n": 7479,
      "win_pct": 2.34,
      "mean_pct": -0.81,
      "mean_dollar": -108.93
    },
    {
      "alert_in_gex_zone": true,
      "side": "call",
      "n": 2516,
      "win_pct": 18.44,
      "mean_pct": 0.02,
      "mean_dollar": 56.4
    },
    {
      "alert_in_gex_zone": true,
      "side": "put",
      "n": 1694,
      "win_pct": 2.89,
      "mean_pct": -0.77,
      "mean_dollar": -134.66
    }
  ],
  "by_gex_position_regime": [
    {
      "regime": "chop",
      "gex_above_or_below": "above_spot",
      "side": "call",
      "n": 2048,
      "win_pct": 13.72,
      "mean_pct": -0.23,
      "mean_dollar": -29.11
    },
    {
      "regime": "chop",
      "gex_above_or_below": "above_spot",
      "side": "put",
      "n": 3033,
      "win_pct": 3.63,
      "mean_pct": -0.7,
      "mean_dollar": -67.34
    },
    {
      "regime": "chop",
      "gex_above_or_below": "below_spot",
      "side": "call",
      "n": 308,
      "win_pct": 22.08,
      "mean_pct": -0.47,
      "mean_dollar": 114.11
    },
    {
      "regime": "chop",
      "gex_above_or_below": "below_spot",
      "side": "put",
      "n": 951,
      "win_pct": 0.63,
      "mean_pct": -0.92,
      "mean_dollar": -219.08
    },
    {
      "regime": "chop",
      "gex_above_or_below": "missing",
      "side": "call",
      "n": 622,
      "win_pct": 24.28,
      "mean_pct": -0.43,
      "mean_dollar": -133.58
    },
    {
      "regime": "chop",
      "gex_above_or_below": "missing",
      "side": "put",
      "n": 1250,
      "win_pct": 5.52,
      "mean_pct": -0.75,
      "mean_dollar": -196.26
    },
    {
      "regime": "mild_trend_up",
      "gex_above_or_below": "above_spot",
      "side": "call",
      "n": 827,
      "win_pct": 39.66,
      "mean_pct": 0.81,
      "mean_dollar": 18.68
    },
    {
      "regime": "mild_trend_up",
      "gex_above_or_below": "above_spot",
      "side": "put",
      "n": 1758,
      "win_pct": 0.17,
      "mean_pct": -0.93,
      "mean_dollar": -63.1
    },
    {
      "regime": "mild_trend_up",
      "gex_above_or_below": "below_spot",
      "side": "call",
      "n": 195,
      "win_pct": 68.72,
      "mean_pct": 2.34,
      "mean_dollar": 854.4
    },
    {
      "regime": "mild_trend_up",
      "gex_above_or_below": "below_spot",
      "side": "put",
      "n": 430,
      "win_pct": 0.0,
      "mean_pct": -0.97,
      "mean_dollar": -138.35
    },
    {
      "regime": "mild_trend_up",
      "gex_above_or_below": "missing",
      "side": "call",
      "n": 338,
      "win_pct": 39.35,
      "mean_pct": -0.1,
      "mean_dollar": 23.98
    },
    {
      "regime": "mild_trend_up",
      "gex_above_or_below": "missing",
      "side": "put",
      "n": 944,
      "win_pct": 0.53,
      "mean_pct": -0.85,
      "mean_dollar": -165.87
    }
  ]
}
